yidong/__init__.py
yidong/client.py
yidong/config.py
yidong/exception.py
yidong/model.py
yidong/util.py
yidong-0.0.21.dist-info/LICENSE
yidong-0.0.21.dist-info/METADATA
yidong-0.0.21.dist-info/WHEEL
yidong-0.0.21.dist-info/entry_points.txt
yidong-0.0.21.dist-info/RECORD
