Metadata-Version: 2.3
Name: yidong
Version: 0.0.21
Summary: 
License: MIT
Author: Yi Team
Author-email: yi@01.ai
Requires-Python: >=3.10,<4.0
Classifier: License :: OSI Approved :: MIT License
Classifier: Programming Language :: Python :: 3
Classifier: Programming Language :: Python :: 3.10
Classifier: Programming Language :: Python :: 3.11
Classifier: Programming Language :: Python :: 3.12
Classifier: Programming Language :: Python :: 3.13
Requires-Dist: httpx (>=0.27.2,<0.28.0)
Requires-Dist: jsonargparse[argcomplete,signatures] (>=4.33.2,<5.0.0)
Requires-Dist: pydantic (>=2.9.2,<3.0.0)
Requires-Dist: pydantic-settings (>=2.5.2,<3.0.0)
Requires-Dist: rich (>=13.9.3,<14.0.0)
